dead_simple_cache/__init__.py
dead_simple_cache/version.py
dead_simple_cache-1.2.2.dist-info/LICENSE
dead_simple_cache-1.2.2.dist-info/METADATA
dead_simple_cache-1.2.2.dist-info/WHEEL
dead_simple_cache-1.2.2.dist-info/top_level.txt
dead_simple_cache-1.2.2.dist-info/zip-safe
dead_simple_cache-1.2.2.dist-info/RECORD
