Metadata-Version: 2.1
Name: dead-simple-cache
Version: 1.2.2
Summary: A dead simple caching lib
Home-page: https://github.com/femelo/dead-simple-cache
Author: Flávio De Melo
Author-email: flavio.eler@gmail.com
License: Apache 2.0
Keywords: caching
License-File: LICENSE
Requires-Dist: rapidfuzz
